{
    "configurations": [
        {
            "name": "Win32",
            "includePath": [
                "${workspaceFolder}/src/**",
                "${workspaceFolder}/lib/**"
            ],
            "defines": [],
            "macFrameworkPath": [],
            "compilerPath": "C:/ProgramData/chocolatey/lib/winlibs/tools/mingw64/bin/g++.exe",
            "cStandard": "gnu17",
            "cppStandard": "c++20",
            "intelliSenseMode": "windows-gcc-x64"
        },
        {
            "name": "Mac",
            "includePath": [
                "${workspaceFolder}/src/**",
                "${workspaceFolder}/lib/**",
                "${workspaceFolder}/build/Debug/_deps/googletest-src/googletest/include/**",
                "${workspaceFolder}/build/Debug/_deps/googletest-src/googlemock/include/**"
            ],
            "defines": [],
            "macFrameworkPath": [],
            "compilerPath": "/opt/homebrew/opt/ccache/libexec/g++-11",
            "cStandard": "gnu17",
            "cppStandard": "c++20",
            "intelliSenseMode": "macos-gcc-x64"
        }
    ],
    "version": 4
}